mnx/__init__.py
ign_mnx-0.0.0.dist-info/METADATA
ign_mnx-0.0.0.dist-info/WHEEL
ign_mnx-0.0.0.dist-info/top_level.txt
ign_mnx-0.0.0.dist-info/RECORD
